setup_py_gen/__init__.py
setup_py_gen-2025.9.81452.dist-info/licenses/LICENSE
setup_py_gen-2025.9.81452.dist-info/METADATA
setup_py_gen-2025.9.81452.dist-info/WHEEL
setup_py_gen-2025.9.81452.dist-info/top_level.txt
setup_py_gen-2025.9.81452.dist-info/RECORD
